{
  "posts": [
    { "id": 1, "title": "Post 1" },
    { "id": 2, "title": "Post 2" },
    { "id": 3, "title": "Post 3" }
  ],
  "comments": [
    { "id": 1, "body": "some comment", "postId": 1 },
    { "id": 2, "body": "some comment", "postId": 1 }
  ],
   "update": {
    { "hotversion":"2.4"},
    { "version":"2.4"},
    { "injection":"\u003cp style=\"float:right\"\u003e\u003ca\u003e公众号享3000万超全题库\u003c/a\u003e|\u003ca href=\"https://cn.nexploren.com/img/wx.jpg\" target='_blank' style=\"color:red;font-weight: bold;\"\u003e立即关注公众号\u003c/a\u003e\u003c/p\u003e"},
    { "enforce":"false"},
    { "url":"https://github.com/CodFrm/cxmooc-tools/releases"}
    }
}
